__init__.py
acceptreject.py
announce.py
auth.py
availability.py
blocking.py
blog.py
bookmarks.py
briar.py
cache.py
categories.py
content.py
context.py
daemon.py
delete.py
devices.py
donate.py
epicyon.py
feeds.py
filters.py
follow.py
followingCalendar.py
git.py
happening.py
httpsig.py
inbox.py
jami.py
like.py
linked_data_sig.py
manualapprove.py
mastoapiv1.py
matrix.py
media.py
metadata.py
migrate.py
newsdaemon.py
newswire.py
outbox.py
person.py
petnames.py
pgp.py
posts.py
pyjsonld.py
question.py
roles.py
schedule.py
session.py
shares.py
skills.py
socnet.py
ssb.py
tests.py
theme.py
threads.py
tox.py
utils.py
webapp_about.py
webapp_calendar.py
webapp_column_left.py
webapp_column_right.py
webapp_confirm.py
webapp_create_post.py
webapp_frontscreen.py
webapp_hashtagswarm.py
webapp_headerbuttons.py
webapp_login.py
webapp_media.py
webapp_moderation.py
webapp_person_options.py
webapp_post.py
webapp_profile.py
webapp_question.py
webapp_search.py
webapp_suspended.py
webapp_timeline.py
webapp_tos.py
webapp_utils.py
webfinger.py
xmpp.py
epicyon-1.2.0.dist-info/LICENSE
epicyon-1.2.0.dist-info/METADATA
epicyon-1.2.0.dist-info/WHEEL
epicyon-1.2.0.dist-info/top_level.txt
epicyon-1.2.0.dist-info/RECORD
