Metadata-Version: 2.1
Name: epicyon
Version: 1.2.0
Summary: A modern ActivityPub compliant server implementing both S2S and C2S protocols.
Home-page: UNKNOWN
Author: Bob Mottram
Author-email: bob@freedombone.net
Maintainer: Bob Mottram
Maintainer-email: bob@freedombone.net
License: GNU Affero General Public License v3
Keywords: epicyon,activitypub,fediverse
Platform: UNKNOWN
Classifier: Development Status :: 5 - Production/Stable
Classifier: License :: OSI Approved :: GNU Affero General Public License v3
Classifier: Programming Language :: Python :: 3
Classifier: Programming Language :: Python :: 3.7
Classifier: Programming Language :: Python :: 3.8
Classifier: Programming Language :: Python :: 3.9
Requires-Dist: crypto (<2,>=1.4.1)
Requires-Dist: idna (<3,>=2.5)
Requires-Dist: numpy (<2,>=1.20.0)
Requires-Dist: pillow (<9,>=8.1.0)
Requires-Dist: pycryptodome (<4,>=3.9.9)
Requires-Dist: pyqrcode (<2,>=1.2.1)
Requires-Dist: python-dateutil (<3,>=2.8.1)
Requires-Dist: requests (<3,>=2.25.1)
Requires-Dist: socks
